{"cameraMode":{"drawMode":0,"name":"Shaded","section":"Shading Mode"},"sceneLighting":true,"audioPlay":false,"sceneViewState":{"m_AlwaysRefresh":false,"showFog":false,"showSkybox":true,"showFlares":true,"showImageEffects":true,"showParticleSystems":true,"showVisualEffectGraphs":true,"m_FxEnabled":true},"in2DMode":false,"pivot":{"x":-11.09691333770752,"y":-5.73272705078125,"z":-6.634864807128906},"rotation":{"x":0.16398796439170838,"y":-0.7847450971603394,"z":0.23404593765735627,"w":0.550067663192749},"size":11.137770652770996,"orthographic":false}